{
    "version": "https://jsonfeed.org/version/1",
    "title": "字节范儿",
    "home_page_url": "http://localhost:4000/feeds/MP_WXS_3293283359.json",
    "description": "字节跳动文化官方账号",
    "icon": "http://wx.qlogo.cn/mmhead/Q3auHgzwzM64Qsrk37lwcfM6lYplhSWIj05hSgiaIicmX2sPZMJ3Tdtg/0",
    "author": {
        "name": "字节范儿"
    },
    "generator": "WeWe-RSS",
    "items": [
        {
            "id": "iuCuo_i2L4A1ByJfypkuKQ",
            "content_html": "",
            "url": "https://mp.weixin.qq.com/s/iuCuo_i2L4A1ByJfypkuKQ",
            "title": "在字节，我们为小鸟做了一件具体的事",
            "image": "https://mmbiz.qpic.cn/sz_mmbiz_jpg/Wl0pfQiav4558Ly0s4eyTqktsKkib4xpgAwIg8ZUrHhxHQD7cKCwZLibs3cLBHicp4FL3Uia0sqicnHMeZL6Jq2jewSibFFEWQuiaYsf6ta4H0klrjo/0?wx_fmt=jpeg",
            "date_modified": "2026-04-22T09:20:23.000Z"
        },
        {
            "id": "1lL1lKzCirj_XfQbJzCbnA",
            "content_html": "",
            "url": "https://mp.weixin.qq.com/s/1lL1lKzCirj_XfQbJzCbnA",
            "title": "字节跳动前沿技术领域人才校招，正式启动！",
            "image": "https://mmbiz.qpic.cn/sz_mmbiz_jpg/Wl0pfQiav457MSPZy9UZ4Lib0R6ALaOpVyRPYNtJxzVPFyhFjKsEmzibIAWj7h54ufK0EzYicias5AMFzZU2TF0CDPgLmYOyTk9vsVUz6ay4dtjk/0?wx_fmt=jpeg",
            "date_modified": "2026-04-16T13:03:31.000Z"
        },
        {
            "id": "1WJYpTxZR50AKB7i0DcfsA",
            "content_html": "",
            "url": "https://mp.weixin.qq.com/s/1WJYpTxZR50AKB7i0DcfsA",
            "title": "7000+Offer、转正率超 50%......字节跳动 ByteIntern 实习生招聘正式启动！",
            "image": "https://mmbiz.qpic.cn/mmbiz_jpg/Wl0pfQiav457qBLnuyfIkuVwdU2Qxu24FvRGX96nBhjyXibek1gcmibpOguJWO8nquCuhO8eyQRsiapGEiaypKNAzfCmxJy2LK4obtAOxVu19c1U/0?wx_fmt=jpeg",
            "date_modified": "2026-03-06T10:10:46.000Z"
        },
        {
            "id": "1C7bJJKj9RAXlilLWDbe_Q",
            "content_html": "",
            "url": "https://mp.weixin.qq.com/s/1C7bJJKj9RAXlilLWDbe_Q",
            "title": "读者调研进行中，填问卷抽字节文创！",
            "image": "https://mmbiz.qpic.cn/mmbiz_jpg/Wl0pfQiav454ibhtsOibbbXMEiaruU3mJiahsxD1e67kvsw4Zib6OGcjDlVv9DiauQBWkhv3o0rhYnYCSXA7WBdz6bHlRMQAtzLedQsyHIju7rWwuY/0?wx_fmt=jpeg",
            "date_modified": "2026-03-06T10:10:46.000Z"
        },
        {
            "id": "DA7By6TeHsMfHWinY95W0g",
            "content_html": "",
            "url": "https://mp.weixin.qq.com/s/DA7By6TeHsMfHWinY95W0g",
            "title": "🧧字节范儿马年定制红包封面来了🧧",
            "image": "https://mmbiz.qpic.cn/mmbiz_jpg/Wl0pfQiav456vibC9K2MKXoHQQOX7nxdU5aNa5Nf5xHJeeibedx9NLIObdLic1HYMB6Od5lSGJbiaZoU925hSVX8v2BSwMp0jeTgkL8Uy08xvxAk/0?wx_fmt=jpeg",
            "date_modified": "2026-02-06T04:33:34.000Z"
        },
        {
            "id": "f8_qlqr0MVAqS0AB0B1WUA",
            "content_html": "",
            "url": "https://mp.weixin.qq.com/s/f8_qlqr0MVAqS0AB0B1WUA",
            "title": "梁汝波分享字节跳动 2026 年度关键词：勇攀高峰",
            "image": "https://mmbiz.qpic.cn/sz_mmbiz_jpg/hrjSjKuhQpUxAaW5bFCRLcYTohRnDxJ8FTOE5lkPm0C8563sUj1gPf1HNxib99ByuUEwtIkKKDiaHStYp2gmShjQ/0?wx_fmt=jpeg",
            "date_modified": "2026-01-29T12:06:00.000Z"
        },
        {
            "id": "apiSOLyyn7C_quCBHT36TQ",
            "content_html": "",
            "url": "https://mp.weixin.qq.com/s/apiSOLyyn7C_quCBHT36TQ",
            "title": "和豆包共同经历的99个瞬间，记录每个人的2025年",
            "image": "https://mmbiz.qpic.cn/sz_mmbiz_jpg/hrjSjKuhQpUNxbAQVZNxibSAAFGyAJwBry2fibJicu6SJFRRWtvKVaRIML0loSJL0wOWFfIbNV00lzhT4eLib4tEjQ/0?wx_fmt=jpeg",
            "date_modified": "2025-12-31T06:06:44.000Z"
        },
        {
            "id": "TlxE5brPnL9xgYe7o8WRQA",
            "content_html": "",
            "url": "https://mp.weixin.qq.com/s/TlxE5brPnL9xgYe7o8WRQA",
            "title": "今年，字节跳动最值得被记住的 20 件事",
            "image": "https://mmbiz.qpic.cn/sz_mmbiz_jpg/hrjSjKuhQpWWvg4Asdgn01IL6Ipb3YOrq38Xr2Rvg4v5aSnxeBaKuaaNASnicAg7lnbAcJawUHHZsHrJFQ6QO1Q/0?wx_fmt=jpeg",
            "date_modified": "2025-12-29T10:06:56.000Z"
        },
        {
            "id": "Y0cxK4d6sOg2fc9z6NxHQQ",
            "content_html": "",
            "url": "https://mp.weixin.qq.com/s/Y0cxK4d6sOg2fc9z6NxHQQ",
            "title": "加入字节跳动六个月之后，我悟了",
            "image": "https://mmbiz.qpic.cn/sz_mmbiz_jpg/hrjSjKuhQpVFD92SY1dLBOlJEvu9l8xMicRvp8SMxFGyUdGiaJ9uSNKXZlmZUB20Zic8WBRbCcicibAH2S9jzllfLibQ/0?wx_fmt=jpeg",
            "date_modified": "2025-12-24T10:07:05.000Z"
        },
        {
            "id": "z5YzVMr1C_aDGZT2zF9J8Q",
            "content_html": "",
            "url": "https://mp.weixin.qq.com/s/z5YzVMr1C_aDGZT2zF9J8Q",
            "title": "不是吧，字节跳动新年礼盒还能这么玩？？！",
            "image": "https://mmbiz.qpic.cn/sz_mmbiz_jpg/hrjSjKuhQpWBoibM9lD5dYcKOmT5wSWvh0bXzWnfWpRHEQURHnqmicea3pHU7LPkhMplHldibF1ANkYS7e1xvLuJA/0?wx_fmt=jpeg",
            "date_modified": "2025-12-19T09:06:07.000Z"
        }
    ]
}