{
    "version": "https://jsonfeed.org/version/1",
    "title": "是小红书人啊",
    "home_page_url": "http://localhost:4000/feeds/MP_WXS_3935671163.json",
    "description": "小红书文化官方账号",
    "icon": "http://wx.qlogo.cn/mmhead/le1D2uwOTUOoHMEYvdsYcyOmlorqdN4eZ8hbiapMqfLEMOyNBPohdib2Sujx2pUGBwRl987lsic9icE/0",
    "author": {
        "name": "是小红书人啊"
    },
    "generator": "WeWe-RSS",
    "items": [
        {
            "id": "WXRLhmfXLqlKpHIwC-hGVw",
            "content_html": "",
            "url": "https://mp.weixin.qq.com/s/WXRLhmfXLqlKpHIwC-hGVw",
            "title": "小红书把艺术展搬进了总部",
            "image": "https://mmbiz.qpic.cn/mmbiz_jpg/xTS6CaSSNhicAn64A1VEK8G12A2N4JqNqpdEffpGeyyzW1pvxmwM6bfGEBAWTgY6icNOBFPiaoQMgiby18km0stAB3SPhmeEOqe6wMukhzKrDdI/0?wx_fmt=jpeg",
            "date_modified": "2026-04-21T03:29:55.000Z"
        },
        {
            "id": "RPRKcO0_aeRgLuqloH8zuw",
            "content_html": "",
            "url": "https://mp.weixin.qq.com/s/RPRKcO0_aeRgLuqloH8zuw",
            "title": "报名！来小红书总部上大师课",
            "image": "https://mmbiz.qpic.cn/sz_mmbiz_jpg/xTS6CaSSNh8Ivk0BRGtJUxEWaajsYLewj4qrjESIqs3iaj46czXibwAYZvcqdRsuLlV66l6whGjt5hAOrt06bzViadJuEQxfvTFQdPeInG3qO0/0?wx_fmt=jpeg",
            "date_modified": "2026-04-13T09:31:49.000Z"
        },
        {
            "id": "62sZ8B938W1DehobmSAGww",
            "content_html": "",
            "url": "https://mp.weixin.qq.com/s/62sZ8B938W1DehobmSAGww",
            "title": "用color walk的方式带你打入小红书内部🎨",
            "image": "https://mmbiz.qpic.cn/mmbiz_jpg/xTS6CaSSNh85o8BVrDRA1XicLp0u3XMf1LLREgvbuxibunQo8kTSYQbmoTTW1vTmbkLoOq9L6B7V76Uo7LZ31Qfpsr0Cbe5ebt6dOAp84apUw/0?wx_fmt=jpeg",
            "date_modified": "2026-03-26T10:25:44.000Z"
        },
        {
            "id": "H273ZQHWd9lyAqMPMxcVEA",
            "content_html": "",
            "url": "https://mp.weixin.qq.com/s/H273ZQHWd9lyAqMPMxcVEA",
            "title": "被小红书工区的角落治愈了100次✨",
            "image": "https://mmbiz.qpic.cn/mmbiz_jpg/xTS6CaSSNhicGRqYGSv9w9CaWmE2d6iakj7xF3hIjFNT0nkuNWKic1MNJsJOswHQQdU8v13Kezia6lgK59ZPLk7gkQ2taQEFcjrytGtxPapibtwE/0?wx_fmt=jpeg",
            "date_modified": "2026-03-13T04:22:23.000Z"
        },
        {
            "id": "MRAYxcYf_-KgFwltc5AADw",
            "content_html": "",
            "url": "https://mp.weixin.qq.com/s/MRAYxcYf_-KgFwltc5AADw",
            "title": "给职场人的健康干货：1 份体检清单、2 种营养、3 个好习惯｜REDacademy",
            "image": "https://mmbiz.qpic.cn/sz_mmbiz_jpg/xTS6CaSSNh9GhVnibgyx5flsbunt3ibS61IicsYqBfiavocmiaawTocUprTfbk3f9ApmYWgbs4hzjPBLabSRSphFibF1TCicLibTbjicXhVGiahLo0GXg/0?wx_fmt=jpeg",
            "date_modified": "2026-03-12T09:30:26.000Z"
        },
        {
            "id": "KsGqJLoExuX5Tfj3apywrQ",
            "content_html": "",
            "url": "https://mp.weixin.qq.com/s/KsGqJLoExuX5Tfj3apywrQ",
            "title": "薯薯家族全员集合！一篇认识小红书的各种「薯」",
            "image": "https://mmbiz.qpic.cn/mmbiz_jpg/xTS6CaSSNh9VsPTTTCHOZuRTu1lz4EeNj1ZMSAJgK5ialnpS2ELwbhDxBkDGHyxI7HWHVpu3qtAwETTctt5t07Y4uANic3tpgH9UFBYqLbnXU/0?wx_fmt=jpeg",
            "date_modified": "2026-03-05T09:30:49.000Z"
        },
        {
            "id": "N4eRwVhahEdSBqj-C1mYCQ",
            "content_html": "",
            "url": "https://mp.weixin.qq.com/s/N4eRwVhahEdSBqj-C1mYCQ",
            "title": "收藏第三年CNY的幕后彩蛋，解锁小红书人的新年好彩头",
            "image": "https://mmbiz.qpic.cn/sz_mmbiz_jpg/xTS6CaSSNhib9k1KgBDRibVOg6J1NM93dGm4HcQPz79S3Os0radqRJsYIfcqia7J4aBruaQdXowQbdpbPfkdMLLWGvFLgqWZM3JyZ8vI1RatYk/0?wx_fmt=jpeg",
            "date_modified": "2026-02-17T08:42:00.000Z"
        },
        {
            "id": "3o8SVkrLyAxnTQnW6sVfpw",
            "content_html": "",
            "url": "https://mp.weixin.qq.com/s/3o8SVkrLyAxnTQnW6sVfpw",
            "title": "这些小红书人的祝福入选「新年福签」啦！",
            "image": "https://mmbiz.qpic.cn/mmbiz_jpg/xTS6CaSSNhicm9fMJqTe7srb8lnqJrtIef2c90gUIicXS3ibzbh93v5rkkKbyrXo8sfQdbD8vD57vdA2L6WTvNPIr62fVac9QEVqiagTGwwtkr0/0?wx_fmt=jpeg",
            "date_modified": "2026-02-16T04:02:55.000Z"
        },
        {
            "id": "uVQ3rbTxCp_mmbL5NBZPeg",
            "content_html": "",
            "url": "https://mp.weixin.qq.com/s/uVQ3rbTxCp_mmbL5NBZPeg",
            "title": "小红书年度诗篇：AI可以有更温柔的去处",
            "image": "https://mmbiz.qpic.cn/sz_mmbiz_jpg/xTS6CaSSNhib8fOWvSJISISmaXxOibb205gSMjNg6YQl7HyIyFYMbWS4T0YdX7JZB10zAibZGzicxCV6gAPFTGGetQk1iaNrcCuJtEZibsJrkZn7I/0?wx_fmt=jpeg",
            "date_modified": "2026-02-14T08:19:17.000Z"
        },
        {
            "id": "1K21LandPHDKE5PWbhCcXA",
            "content_html": "",
            "url": "https://mp.weixin.qq.com/s/1K21LandPHDKE5PWbhCcXA",
            "title": "小红书语音幕后：一位博士用5年把冷门技术送上小红书C位",
            "image": "https://mmbiz.qpic.cn/sz_mmbiz_jpg/xTS6CaSSNh8QTQpO1Vk7UK0HIVKGrrvfc87CiaVZGhw9laXOYXmCqibMCaA4mYOd10xLtQLGneDvy6f0Ticfhon6hGy92uOHjnCnTtgCedLde4/0?wx_fmt=jpeg",
            "date_modified": "2026-02-13T10:07:13.000Z"
        }
    ]
}